brainchain/README.md
brainchain/__init__.py
brainchain/agents/state/agent_state.py
brainchain/agents/state/state_manager.py
brainchain/assistants.py
brainchain/brainchain.py
brainchain/carnivore.py
brainchain/coredata.py
brainchain/embeddings.py
brainchain/graph/base.py
brainchain/graph/schema.py
brainchain/products.py
brainchain/requirements.txt
brainchain/sales_intel.py
brainchain/search_v2.py
brainchain/tools/__init__.py
brainchain/tools/coding.py
brainchain/tools/diffbot.py
brainchain/tools/factual.py
brainchain/tools/fts.py
brainchain/tools/graph.py
brainchain/tools/memory.py
brainchain/tools/plan.py
brainchain/tools/tokens.py
brainchain/tools/tools.py
brainchain/tools/web.py
brainchain/tools.py
brainchain/webapp/__init__.py
brainchain/webapp/agents.py
brainchain/webapp/base.py
brainchain/webapp/business_ideas.py
brainchain/webapp/contents.py
brainchain/webapp/conversations.py
brainchain/webapp/embedding_models.py
brainchain/webapp/embeddings.py
brainchain/webapp/files.py
brainchain/webapp/health.py
brainchain/webapp/language_models.py
brainchain/webapp/laws.py
brainchain/webapp/messages.py
brainchain/webapp/namespaces.py
brainchain/webapp/programs.py
brainchain/webapp/tasks.py
brainchain/webapp/tools.py
brainchain/webapp/users.py
brainchain-0.9.5.dist-info/METADATA
brainchain-0.9.5.dist-info/WHEEL
brainchain-0.9.5.dist-info/RECORD
