Metadata-Version: 2.1
Name: brainchain
Version: 0.9.5
Summary: Brainchain API client
Author: Arthur M. Collé
Author-email: arthur@brainchain.ai
Requires-Python: >=3.9,<4.0
Classifier: Programming Language :: Python :: 3
Classifier: Programming Language :: Python :: 3.9
Classifier: Programming Language :: Python :: 3.10
Classifier: Programming Language :: Python :: 3.11
Provides-Extra: mlx
Provides-Extra: mlx-embedding-models
Requires-Dist: bottleneck (>=1.3.6,<2.0.0)
Requires-Dist: modal-client (==0.62.180)
Requires-Dist: pandas (>=2.1.0,<3.0.0)
Requires-Dist: requests (>=2.31.0,<3.0.0)
Requires-Dist: tiktoken (>=0.5.0)
Requires-Dist: torch (>=2.3.1,<3.0.0)
Requires-Dist: transformers (>=4.38.0)
Requires-Dist: urllib3 (>=1.25.4)
Requires-Dist: watchtower (==3.0.1)
